omero_marshal/__init__.py
omero_marshal/decode/__init__.py
omero_marshal/decode/decoders/__init__.py
omero_marshal/decode/decoders/acquisitionmode.py
omero_marshal/decode/decoders/affinetransform.py
omero_marshal/decode/decoders/annotation.py
omero_marshal/decode/decoders/boolean_annotation.py
omero_marshal/decode/decoders/channel.py
omero_marshal/decode/decoders/checksum_algorithm.py
omero_marshal/decode/decoders/comment_annotation.py
omero_marshal/decode/decoders/contrastmethod.py
omero_marshal/decode/decoders/dataset.py
omero_marshal/decode/decoders/details.py
omero_marshal/decode/decoders/dimensionorder.py
omero_marshal/decode/decoders/double_annotation.py
omero_marshal/decode/decoders/ellipse.py
omero_marshal/decode/decoders/enum.py
omero_marshal/decode/decoders/experimenter.py
omero_marshal/decode/decoders/experimentergroup.py
omero_marshal/decode/decoders/externalinfo.py
omero_marshal/decode/decoders/file_annotation.py
omero_marshal/decode/decoders/format.py
omero_marshal/decode/decoders/illumination.py
omero_marshal/decode/decoders/image.py
omero_marshal/decode/decoders/label.py
omero_marshal/decode/decoders/line.py
omero_marshal/decode/decoders/long_annotation.py
omero_marshal/decode/decoders/map_annotation.py
omero_marshal/decode/decoders/mask.py
omero_marshal/decode/decoders/original_file.py
omero_marshal/decode/decoders/permissions.py
omero_marshal/decode/decoders/photometricinterpretation.py
omero_marshal/decode/decoders/pixels.py
omero_marshal/decode/decoders/pixelstype.py
omero_marshal/decode/decoders/plate.py
omero_marshal/decode/decoders/plateacquisition.py
omero_marshal/decode/decoders/point.py
omero_marshal/decode/decoders/polygon.py
omero_marshal/decode/decoders/polyline.py
omero_marshal/decode/decoders/project.py
omero_marshal/decode/decoders/rectangle.py
omero_marshal/decode/decoders/roi.py
omero_marshal/decode/decoders/screen.py
omero_marshal/decode/decoders/shape.py
omero_marshal/decode/decoders/tag_annotation.py
omero_marshal-0.9.0.dist-info/LICENSE.txt
omero_marshal-0.9.0.dist-info/METADATA
omero_marshal-0.9.0.dist-info/WHEEL
omero_marshal-0.9.0.dist-info/entry_points.txt
omero_marshal-0.9.0.dist-info/top_level.txt
omero_marshal-0.9.0.dist-info/zip-safe
omero_marshal-0.9.0.dist-info/RECORD
