Metadata-Version: 2.1
Name: omero-marshal
Version: 0.9.0
Summary: OMERO Marshal
Home-page: https://github.com/ome/omero-marshal
Author: The Open Microscopy Team, Glencoe Software, Inc.
Author-email: ome-devel@lists.openmicroscopy.org.uk
License: GPLv2+
Platform: any
Classifier: Development Status :: 5 - Production/Stable
Classifier: Intended Audience :: Developers
Classifier: License :: OSI Approved :: GNU General Public License v2 or later (GPLv2+)
Classifier: Natural Language :: English
Classifier: Operating System :: OS Independent
Classifier: Programming Language :: Python :: 3
Classifier: Topic :: Software Development :: Libraries :: Python Modules
Requires-Python: >=3
License-File: LICENSE.txt
